HOLA/__init__.py
HOLA/base.py
PyHOLA-0.1.2110.dist-info/LICENSE
PyHOLA-0.1.2110.dist-info/METADATA
PyHOLA-0.1.2110.dist-info/WHEEL
PyHOLA-0.1.2110.dist-info/top_level.txt
PyHOLA-0.1.2110.dist-info/RECORD
