Metadata-Version: 2.1
Name: PyHOLA
Version: 0.1.2110
Summary: A Python implementation to download sensor data using HOLOGRAM API
Home-page: https://github.com/daquinterop/PyHOLA
Author: Diego Quintero
Author-email: dquintero@nevada.unr.edu
License: MIT
Platform: UNKNOWN
License-File: LICENSE
